nf_grapher/__init__.py
nf_grapher/encoder.py
nf_grapher/score.py
nf_grapher/typed.py
nf_grapher/typedNode.py
nf_grapher/util.py
nf_grapher-1.2.24.dist-info/DESCRIPTION.rst
nf_grapher-1.2.24.dist-info/METADATA
nf_grapher-1.2.24.dist-info/RECORD
nf_grapher-1.2.24.dist-info/WHEEL
nf_grapher-1.2.24.dist-info/metadata.json
nf_grapher-1.2.24.dist-info/top_level.txt
test/__init__.py
test/test_score.py
