Metadata-Version: 2.0
Name: nf-grapher
Version: 1.2.24
Summary: A library for building Native Format Scores.
Home-page: https://ghe.spotify.net/NativeFormat/nf-grapher
Author: The Native Format Team
License: UNKNOWN
Platform: UNKNOWN
Classifier: Programming Language :: Python :: 3
Classifier: Operating System :: OS Independent
Requires-Python: >=3.3
Requires-Dist: marshmallow (==3.0.0b11)
